axonsuite/__init__.py
axonsuite/cli.py
axonsuite-0.1.0.dist-info/licenses/LICENSE
axonsuite-0.1.0.dist-info/METADATA
axonsuite-0.1.0.dist-info/WHEEL
axonsuite-0.1.0.dist-info/entry_points.txt
axonsuite-0.1.0.dist-info/top_level.txt
axonsuite-0.1.0.dist-info/RECORD
