Metadata-Version: 2.4
Name: axonsuite
Version: 0.1.0
Summary: AxonSuite: Curated ML & DL collections you can install in one command.
Author-email: Preetha M <preethamurugesan2021@gmail.com>
License: MIT
Keywords: machine-learning,deep-learning,pip,setup,education,hackathon
Classifier: Programming Language :: Python :: 3
Classifier: License :: OSI Approved :: MIT License
Classifier: Operating System :: OS Independent
Requires-Python: >=3.9
License-File: LICENSE
Provides-Extra: ml-basic
Requires-Dist: numpy==1.26.4; extra == "ml-basic"
Requires-Dist: pandas==2.2.2; extra == "ml-basic"
Requires-Dist: scikit-learn==1.5.2; extra == "ml-basic"
Requires-Dist: scipy==1.13.1; extra == "ml-basic"
Requires-Dist: matplotlib==3.9.0; extra == "ml-basic"
Requires-Dist: seaborn==0.13.2; extra == "ml-basic"
Requires-Dist: joblib==1.4.2; extra == "ml-basic"
Requires-Dist: openpyxl==3.1.5; extra == "ml-basic"
Requires-Dist: tqdm==4.66.4; extra == "ml-basic"
Provides-Extra: ml-advanced
Requires-Dist: xgboost==2.1.1; extra == "ml-advanced"
Requires-Dist: lightgbm==4.3.0; extra == "ml-advanced"
Requires-Dist: catboost==1.2.5; extra == "ml-advanced"
Requires-Dist: category-encoders==2.6.3; extra == "ml-advanced"
Requires-Dist: imbalanced-learn==0.12.3; extra == "ml-advanced"
Requires-Dist: feature-engine==1.8.1; extra == "ml-advanced"
Provides-Extra: dl-basic
Requires-Dist: tensorflow==2.17.0; extra == "dl-basic"
Requires-Dist: torch==2.4.0; extra == "dl-basic"
Provides-Extra: dl-advanced
Requires-Dist: torchvision==0.19.0; extra == "dl-advanced"
Requires-Dist: torchaudio==2.4.0; extra == "dl-advanced"
Requires-Dist: tensorflow-probability==0.24.0; extra == "dl-advanced"
Requires-Dist: einops==0.7.0; extra == "dl-advanced"
Requires-Dist: transformers==4.43.3; extra == "dl-advanced"
Provides-Extra: viz
Requires-Dist: plotly==5.24.0; extra == "viz"
Requires-Dist: pydot==1.4.2; extra == "viz"
Requires-Dist: graphviz==0.20.3; extra == "viz"
Provides-Extra: nlp
Requires-Dist: nltk==3.9.1; extra == "nlp"
Requires-Dist: gensim==4.3.3; extra == "nlp"
Requires-Dist: spacy==3.7.5; extra == "nlp"
Requires-Dist: datasets==2.20.0; extra == "nlp"
Requires-Dist: transformers==4.43.3; extra == "nlp"
Provides-Extra: utils
Requires-Dist: python-dotenv==1.0.1; extra == "utils"
Requires-Dist: requests==2.32.3; extra == "utils"
Provides-Extra: all
Requires-Dist: axonsuite[dl-advanced,dl-basic,ml-advanced,ml-basic,nlp,utils,viz]; extra == "all"
Dynamic: license-file
